nendo_plugin_voicegen_styletts2/__init__.py
nendo_plugin_voicegen_styletts2/config.py
nendo_plugin_voicegen_styletts2/plugin.py
nendo_plugin_voicegen_styletts2/styletts2/Modules/__init__.py
nendo_plugin_voicegen_styletts2/styletts2/Modules/diffusion/__init__.py
nendo_plugin_voicegen_styletts2/styletts2/Modules/diffusion/diffusion.py
nendo_plugin_voicegen_styletts2/styletts2/Modules/diffusion/modules.py
nendo_plugin_voicegen_styletts2/styletts2/Modules/diffusion/sampler.py
nendo_plugin_voicegen_styletts2/styletts2/Modules/diffusion/utils.py
nendo_plugin_voicegen_styletts2/styletts2/Modules/discriminators.py
nendo_plugin_voicegen_styletts2/styletts2/Modules/hifigan.py
nendo_plugin_voicegen_styletts2/styletts2/Modules/istftnet.py
nendo_plugin_voicegen_styletts2/styletts2/Utils/ASR/__init__.py
nendo_plugin_voicegen_styletts2/styletts2/Utils/ASR/config.yml
nendo_plugin_voicegen_styletts2/styletts2/Utils/ASR/layers.py
nendo_plugin_voicegen_styletts2/styletts2/Utils/ASR/models.py
nendo_plugin_voicegen_styletts2/styletts2/Utils/JDC/__init__.py
nendo_plugin_voicegen_styletts2/styletts2/Utils/JDC/model.py
nendo_plugin_voicegen_styletts2/styletts2/Utils/PLBERT/config.yml
nendo_plugin_voicegen_styletts2/styletts2/Utils/PLBERT/util.py
nendo_plugin_voicegen_styletts2/styletts2/Utils/__init__.py
nendo_plugin_voicegen_styletts2/styletts2/__init__.py
nendo_plugin_voicegen_styletts2/styletts2/api.py
nendo_plugin_voicegen_styletts2/styletts2/models.py
nendo_plugin_voicegen_styletts2/styletts2/styletts2_config.yaml
nendo_plugin_voicegen_styletts2/styletts2/text_utils.py
nendo_plugin_voicegen_styletts2/styletts2/utils.py
nendo_plugin_voicegen_styletts2/styletts2/voices/f-us-1.wav
nendo_plugin_voicegen_styletts2/styletts2/voices/f-us-2.wav
nendo_plugin_voicegen_styletts2/styletts2/voices/f-us-3.wav
nendo_plugin_voicegen_styletts2/styletts2/voices/f-us-4.wav
nendo_plugin_voicegen_styletts2/styletts2/voices/m-us-1.wav
nendo_plugin_voicegen_styletts2/styletts2/voices/m-us-2.wav
nendo_plugin_voicegen_styletts2-0.1.1.dist-info/METADATA
nendo_plugin_voicegen_styletts2-0.1.1.dist-info/WHEEL
nendo_plugin_voicegen_styletts2-0.1.1.dist-info/RECORD
