Metadata-Version: 2.1
Name: nendo-plugin-voicegen-styletts2
Version: 0.1.1
Summary: A text to speech plugin based on StyleTTS2.
Home-page: https://okio.ai
License: MIT
Keywords: AI,ML,generative,music,okio,nendo,audio generation,TTS,StyleTTS2,text to speech,zero-shot voice cloning,voice cloning
Author: Aaron Abebe
Author-email: aaron@okio.ai
Requires-Python: >=3.8,<3.11
Classifier: Development Status :: 5 - Production/Stable
Classifier: Intended Audience :: Developers
Classifier: License :: OSI Approved :: MIT License
Classifier: Operating System :: OS Independent
Classifier: Programming Language :: Python :: 3
Classifier: Programming Language :: Python :: 3.8
Classifier: Programming Language :: Python :: 3.9
Classifier: Programming Language :: Python :: 3.10
Classifier: Topic :: Multimedia :: Sound/Audio
Requires-Dist: einops (>=0.7.0,<0.8.0)
Requires-Dist: einops-exts (>=0.0.4,<0.0.5)
Requires-Dist: librosa (>=0.10.0,<0.11.0)
Requires-Dist: munch (>=4.0.0,<5.0.0)
Requires-Dist: nendo (>=0.2.0,<0.3.0)
Requires-Dist: nltk (>=3.8.1,<4.0.0)
Requires-Dist: phonemizer (>=3.2.1,<4.0.0)
Requires-Dist: pydantic (>=2.4.2,<3.0.0)
Requires-Dist: tortoise-tts (>=3.0.0,<4.0.0)
Project-URL: Repository, https://github.com/okio-ai/nendo_plugin_voicegen_styletts2
